sphinx_terraform/__init__.py
sphinx_terraform/code.py
sphinx_terraform/i18n.py
sphinx_terraform/markup.py
sphinx_terraform/py.typed
sphinx_terraform/sphinxapi.py
sphinx_terraform/terraform.py
sphinx_terraform/viewcode/__init__.py
sphinx_terraform/viewcode/html.py
sphinxcontrib_terraform-0.2.dist-info/LICENSE
sphinxcontrib_terraform-0.2.dist-info/METADATA
sphinxcontrib_terraform-0.2.dist-info/WHEEL
sphinxcontrib_terraform-0.2.dist-info/top_level.txt
sphinxcontrib_terraform-0.2.dist-info/RECORD
